kolat-2.0.0.dist-info/METADATA
kolat-2.0.0.dist-info/WHEEL
kolat-2.0.0.dist-info/licenses/LICENSE
kolat.libs/libcom_err-2abe824b.so.2
kolat.libs/libcrypto-d3570994.so.10
kolat.libs/libgssapi_krb5-497db0c6.so.2
kolat.libs/libk5crypto-b1f99d5c.so.3
kolat.libs/libkeyutils-dfe70bd6.so.1
kolat.libs/libkrb5-fcafa220.so.3
kolat.libs/libkrb5support-d0bcff84.so.0
kolat.libs/libpcre-9513aab5.so.1
kolat.libs/libselinux-0922c95c.so.1
kolat.libs/libssl-cd1d6220.so.10
kolat/__init__.py
kolat/kolat.cpython-313-x86_64-linux-gnu.so
rust-toolchain.toml
kolat-2.0.0.dist-info/RECORD
